kawaii_traceback-0.3.3.dist-info/licenses/LICENSE
kawaiitb/__init__.py
kawaiitb/_default_config.py
kawaiitb/autoload.py
kawaiitb/kraceback.py
kawaiitb/kwihandler.py
kawaiitb/runtimeconfig.py
kawaiitb/tools.py
kawaiitb/handlers/__init__.py
kawaiitb/handlers/extensions.py
kawaiitb/handlers/vanilla.py
kawaiitb/handlers/defaults/__init__.py
kawaiitb/handlers/defaults/assertionerror.py
kawaiitb/handlers/defaults/attributeerror.py
kawaiitb/handlers/defaults/eoferror.py
kawaiitb/handlers/defaults/importerror.py
kawaiitb/handlers/defaults/keyboardinterrupt.py
kawaiitb/handlers/defaults/overflowerror.py
kawaiitb/handlers/defaults/stopasynciteration.py
kawaiitb/handlers/defaults/stopiteration.py
kawaiitb/handlers/defaults/systemexit.py
kawaiitb/handlers/defaults/zerodivisionerror.py
kawaiitb/utils/__init__.py
kawaiitb/utils/ast_parse.py
kawaiitb/utils/fromtraceback.py
kawaiitb/utils/suggestions.py
kawaiitb/utils/utils.py
kawaii_traceback-0.3.3.dist-info/METADATA
kawaii_traceback-0.3.3.dist-info/WHEEL
kawaii_traceback-0.3.3.dist-info/top_level.txt
kawaii_traceback-0.3.3.dist-info/RECORD
