Metadata-Version: 2.4
Name: kawaii-traceback
Version: 0.3.3
Summary: Cute Python traceback beautifier with multilingual support
Author-email: BPuffer <mc-puffer@qq.com>
License-Expression: MIT
Project-URL: Homepage, https://github.com/bpuffer/kawaii-traceback
Keywords: traceback,debug,error-handling
Classifier: Development Status :: 3 - Alpha
Classifier: Intended Audience :: Developers
Classifier: Programming Language :: Python :: 3
Classifier: Programming Language :: Python :: 3.11
Classifier: Programming Language :: Python :: 3.12
Classifier: Programming Language :: Python :: 3.13
Classifier: Operating System :: OS Independent
Requires-Python: >=3.11
License-File: LICENSE
Requires-Dist: astroid>=3.3.10
Provides-Extra: test
Requires-Dist: pytest>=7.0.0; extra == "test"
Requires-Dist: pytest-asyncio>=0.23.0; extra == "test"
Requires-Dist: numpy==2.3.3; extra == "test"
Requires-Dist: pyyaml==6.0.3; extra == "test"
Dynamic: license-file
